pybpsapi/__init__.py
pybpsapi/main.py
pybpsapi-1.5.0.dist-info/METADATA
pybpsapi-1.5.0.dist-info/WHEEL
pybpsapi-1.5.0.dist-info/licenses/LICENSE
pybpsapi-1.5.0.dist-info/RECORD
