Metadata-Version: 2.4
Name: pybpsapi
Version: 1.5.0
Summary: This package is a Python wrapper for the BPS Circular API. It supports all the five endpoints of the API, and also contains a good circular-checking system.
License-Expression: MIT
License-File: LICENSE
Keywords: api,bps,bpsapi,python,python3,wrapper
Requires-Python: >=3.10
Requires-Dist: requests
